plabic/__init__.py
plabic/__main__.py
plabic/ba_permutation.py
plabic/bcfw_cell.py
plabic/cluster.py
plabic/cyclic_utils.py
plabic/demazure.py
plabic/double_wiring.py
plabic/framed_2_disks.py
plabic/le_diagram.py
plabic/ownership_workarounds.py
plabic/plabic_diagram.py
plabic/plabic_diagram_faced.py
plabic/planar_diagram.py
plabic/separated_sets.py
plabic/shuffle.py
plabic/sign_pattern.py
plabic/sym_utils.py
plabic/symbol_alphabet.py
plabic/tnn_grassmannian.py
plabic/triangulation.py
plabic-0.3.3.dist-info/licenses/LICENSE
plabic-0.3.3.dist-info/METADATA
plabic-0.3.3.dist-info/WHEEL
plabic-0.3.3.dist-info/top_level.txt
plabic-0.3.3.dist-info/RECORD
