Metadata-Version: 2.4
Name: plabic
Version: 0.3.3
Summary: A package related to the cluster algebra and geometry related to plabic graphs
Author-email: Ammar Husain <ammar.s.husain@gmail.com>
Project-URL: Homepage, https://github.com/Cobord/Plabic
Project-URL: Bug Tracker, https://github.com/Cobord/Plabic/issues
Classifier: Programming Language :: Python :: 3
Classifier: License :: OSI Approved :: GNU General Public License v3 (GPLv3)
Classifier: Topic :: Scientific/Engineering :: Mathematics
Classifier: Topic :: Scientific/Engineering :: Physics
Classifier: Intended Audience :: Science/Research
Requires-Python: >=3.11
License-File: LICENSE
Requires-Dist: matplotlib>=3.10.5
Requires-Dist: networkx>=3.5
Requires-Dist: numpy>=2.3.2
Requires-Dist: pillow>=11.3.0
Requires-Dist: pylint>=3.3.8
Requires-Dist: pyside6>=6.9.1
Requires-Dist: pytest>=8.4.1
Requires-Dist: sympy>=1.14.0
Requires-Dist: testresources>=2.0.2
Dynamic: license-file
